myMathPackage/__init__.py
myMathPackage/chooseYourOption.py
myMathPackage-0.0.3.dist-info/LICENCE
myMathPackage-0.0.3.dist-info/METADATA
myMathPackage-0.0.3.dist-info/WHEEL
myMathPackage-0.0.3.dist-info/top_level.txt
myMathPackage-0.0.3.dist-info/RECORD
