Metadata-Version: 2.1
Name: myMathPackage
Version: 0.0.3
Summary: A small math package
Home-page: https://github.com/pypa/sampleproject
Author: Michael Heser
Author-email: hesermi71995@th-nuernberg.de
License: UNKNOWN
Platform: UNKNOWN
Classifier: Programming Language :: Python :: 3
Classifier: License :: OSI Approved :: MIT License
Classifier: Operating System :: OS Independent
Requires-Python: >=3.0
